Radial_bias_Raunak_gola/__init__.py
Radial_bias_Raunak_gola/module.py
Radial_Bias-0.1.2.dist-info/LICENSE
Radial_Bias-0.1.2.dist-info/METADATA
Radial_Bias-0.1.2.dist-info/WHEEL
Radial_Bias-0.1.2.dist-info/top_level.txt
Radial_Bias-0.1.2.dist-info/RECORD
